attempts/__init__.py
attempts/main.py
attempts-0.2.2.dist-info/LICENSE
attempts-0.2.2.dist-info/METADATA
attempts-0.2.2.dist-info/WHEEL
attempts-0.2.2.dist-info/top_level.txt
attempts-0.2.2.dist-info/RECORD
