Metadata-Version: 2.1
Name: attempts
Version: 0.2.2
Summary: A simple yet customizable Python package to automatically replace your print statements with timestamped versions.
Home-page: https://github.com/pedrotcp/attempts
Author: Pedro Henrique Bezerra
Author-email: pedrotcp@gmail.com
Classifier: Programming Language :: Python :: 3
Classifier: License :: OSI Approved :: MIT License
Classifier: Operating System :: OS Independent
Requires-Python: >=3.6
License-File: LICENSE
Requires-Dist: colorama>=0.4.4
